oemetadata/__init__.py
oemetadata/json_schema/README.md
oemetadata/json_schema/__init__.py
oemetadata/json_schema/draft07/__init__.py
oemetadata/json_schema/draft07/schema.json
oemetadata/json_schema/draft07/schema.json.license
oemetadata/json_schema/draft07/schema.py
oemetadata/json_schema/draft2020_12/__init__.py
oemetadata/json_schema/draft2020_12/schema.json
oemetadata/json_schema/draft2020_12/schema.json.license
oemetadata/json_schema/draft2020_12/schema.py
oemetadata/latest/README.md
oemetadata/latest/__init__.py
oemetadata/latest/context.json
oemetadata/latest/example.json
oemetadata/latest/example.py
oemetadata/latest/metadata_key_description.md
oemetadata/latest/schema.json
oemetadata/latest/schema.py
oemetadata/latest/template.json
oemetadata/latest/template.py
oemetadata/v1/__init__.py
oemetadata/v1/v130/__init__.py
oemetadata/v1/v130/example.json
oemetadata/v1/v130/example.py
oemetadata/v1/v130/schema.json
oemetadata/v1/v130/schema.py
oemetadata/v1/v130/template.json
oemetadata/v1/v130/template.py
oemetadata/v1/v140/__init__.py
oemetadata/v1/v140/example.json
oemetadata/v1/v140/example.py
oemetadata/v1/v140/metadata_key_description.md
oemetadata/v1/v140/schema.json
oemetadata/v1/v140/schema.py
oemetadata/v1/v140/template.json
oemetadata/v1/v140/template.py
oemetadata/v1/v141/__init__.py
oemetadata/v1/v141/example.json
oemetadata/v1/v141/example.py
oemetadata/v1/v141/metadata_key_description.md
oemetadata/v1/v141/schema.json
oemetadata/v1/v141/schema.py
oemetadata/v1/v141/template.json
oemetadata/v1/v141/template.py
oemetadata/v1/v150/README.md
oemetadata/v1/v150/__init__.py
oemetadata/v1/v150/context.json
oemetadata/v1/v150/example.json
oemetadata/v1/v150/example.py
oemetadata/v1/v150/metadata_key_description.md
oemetadata/v1/v150/schema.json
oemetadata/v1/v150/schema.py
oemetadata/v1/v150/template.json
oemetadata/v1/v150/template.py
oemetadata/v1/v151/README.md
oemetadata/v1/v151/__init__.py
oemetadata/v1/v151/context.json
oemetadata-2.0.4.dist-info/licenses/LICENSE.txt
oemetadata-2.0.4.dist-info/WHEEL
oemetadata-2.0.4.dist-info/METADATA
oemetadata-2.0.4.dist-info/RECORD
