Metadata-Version: 2.4
Name: oemetadata
Version: 2.0.4
Summary: Open Energy Metadata (OEMetadata) - The energy metadata standard
Author-email: Ludwig Hülk <datenzentrum@rl-institut.de>
Requires-Python: >=3.10
Classifier: Development Status :: 4 - Beta
Classifier: License :: OSI Approved :: MIT License
Classifier: Natural Language :: English
Classifier: Operating System :: OS Independent
Classifier: Programming Language :: Python :: 3
Classifier: Programming Language :: Python :: 3.10
License-File: LICENSE.txt
Requires-Dist: stringcase ~=1.2.0
Project-URL: Documentation, https://openenergyplatform.github.io/oemetadata/latest/
Project-URL: Homepage, https://github.com/OpenEnergyPlatform/oemetadata
Project-URL: Source, https://github.com/OpenEnergyPlatform/oemetadata
